mathMB/__init__.py
mathMB/fit_model.py
mathMB/histogram.py
mathMB/interpu.py
mathMB/minmaxmean.py
mathMB/randomdeviates.py
mathMB/rotation_matrix.py
mathMB/smooth.py
mathMB/version.py
mathMB/tests/__init__.py
mathMB/tests/test_interpu.py
mymath/RotationMatrix.py
mymath/__init__.py
mymath/interpu.py
mymath/minmaxmean.py
mymath/randomdeviates.py
mymath/rotation_matrix.py
mathMB-1.10.dist-info/METADATA
mathMB-1.10.dist-info/WHEEL
mathMB-1.10.dist-info/top_level.txt
mathMB-1.10.dist-info/RECORD
