Metadata-Version: 2.1
Name: mathMB
Version: 1.10
Summary: Mathematical procedures for nexoclom and general use
Home-page: https://github.com/mburger-stsci/mathMB
Author: Matthew Burger
Author-email: mburger@stsci.edu
License: BSD 3-Clause
Platform: UNKNOWN
Requires-Python: >=3.6
Requires-Dist: numpy
Requires-Dist: scipy
